iotloranode.py
iotloranode-0.0.3.dist-info/DESCRIPTION.rst
iotloranode-0.0.3.dist-info/METADATA
iotloranode-0.0.3.dist-info/RECORD
iotloranode-0.0.3.dist-info/WHEEL
iotloranode-0.0.3.dist-info/metadata.json
iotloranode-0.0.3.dist-info/top_level.txt
