Metadata-Version: 2.0
Name: iotloranode
Version: 0.0.3
Summary: IoT LoRa Node pHAT Python Library
Home-page: https://github.com/PiSupply/rak811-python
Author: Pi Supply
Author-email: Ryan@pi-supply.com
License: GNU GPL V3
Keywords: Raspberry Pi IoT LoRa Node TheThingsNetwork TTN
Platform: UNKNOWN
Classifier: Development Status :: 3 - Alpha
Classifier: Intended Audience :: Developers
Classifier: Topic :: Education
Classifier: Topic :: System :: Hardware
Classifier: Topic :: Software Development
Classifier: License :: OSI Approved :: GNU Lesser General Public License v3 (LGPLv3)
Classifier: Programming Language :: Python :: 3
Classifier: Programming Language :: Python :: 3.3
Classifier: Programming Language :: Python :: 3.4
Classifier: Programming Language :: Python :: 3.5
Classifier: Programming Language :: Python :: 3.6
Provides-Extra: dev
Provides-Extra: test
Requires-Dist: setuptools
Requires-Dist: wheel
Requires-Dist: pyserial (>=3)
Requires-Dist: future
Provides-Extra: dev
Requires-Dist: check-manifest; extra == 'dev'
Provides-Extra: test
Requires-Dist: coverage; extra == 'test'
